{
  "__inputs": [],
  "__requires": [
    {
      "type": "panel",
      "id": "gauge",
      "name": "Gauge",
      "version": ""
    },
    {
      "type": "grafana",
      "id": "grafana",
      "name": "Grafana",
      "version": "7.5.6"
    },
    {
      "type": "panel",
      "id": "graph",
      "name": "Graph",
      "version": ""
    },
    {
      "type": "panel",
      "id": "stat",
      "name": "Stat",
      "version": ""
    },
    {
      "type": "panel",
      "id": "yesoreyeram-boomtheme-panel",
      "name": "Boom Theme",
      "version": "0.1.1"
    }
  ],
  "annotations": {
    "list": [
      {
        "builtIn": 1,
        "datasource": "-- Grafana --",
        "enable": true,
        "hide": true,
        "iconColor": "rgba(0, 211, 255, 1)",
        "name": "Annotations & Alerts",
        "type": "dashboard"
      }
    ]
  },
  "editable": true,
  "gnetId": null,
  "graphTooltip": 0,
  "id": null,
  "links": [],
  "panels": [
    {
      "datasource": null,
      "fieldConfig": {
        "defaults": {
          "color": {
            "mode": "thresholds"
          },
          "mappings": [],
          "thresholds": {
            "mode": "absolute",
            "steps": [
              {
                "color": "dark-green",
                "value": null
              }
            ]
          }
        },
        "overrides": []
      },
      "gridPos": {
        "h": 3,
        "w": 2,
        "x": 0,
        "y": 0
      },
      "id": 9,
      "options": {
        "colorMode": "value",
        "graphMode": "area",
        "justifyMode": "center",
        "orientation": "auto",
        "reduceOptions": {
          "calcs": [
            "lastNotNull"
          ],
          "fields": "",
          "values": false
        },
        "text": {},
        "textMode": "auto"
      },
      "pluginVersion": "7.5.6",
      "targets": [
        {
          "application": {
            "filter": "/.*/"
          },
          "functions": [],
          "group": {
            "filter": "Zabbix servers"
          },
          "host": {
            "filter": "Zabbix server"
          },
          "item": {
            "filter": "System name"
          },
          "options": {
            "showDisabledItems": false,
            "skipEmptyValues": false
          },
          "proxy": {
            "filter": ""
          },
          "queryType": 2,
          "refId": "A",
          "resultFormat": "time_series",
          "table": {
            "skipEmptyValues": false
          },
          "tags": {
            "filter": ""
          },
          "trigger": {
            "filter": ""
          },
          "triggers": {
            "acknowledged": 2,
            "count": true,
            "minSeverity": 3
          }
        }
      ],
      "type": "stat"
    },
    {
      "datasource": null,
      "fieldConfig": {
        "defaults": {
          "color": {
            "mode": "thresholds"
          },
          "mappings": [],
          "thresholds": {
            "mode": "absolute",
            "steps": [
              {
                "color": "dark-green",
                "value": null
              }
            ]
          }
        },
        "overrides": []
      },
      "gridPos": {
        "h": 3,
        "w": 2,
        "x": 2,
        "y": 0
      },
      "id": 10,
      "options": {
        "colorMode": "value",
        "graphMode": "none",
        "justifyMode": "center",
        "orientation": "auto",
        "reduceOptions": {
          "calcs": [
            "lastNotNull"
          ],
          "fields": "",
          "values": false
        },
        "text": {},
        "textMode": "auto"
      },
      "pluginVersion": "7.5.6",
      "targets": [
        {
          "application": {
            "filter": "/.*/"
          },
          "functions": [],
          "group": {
            "filter": "Zabbix servers"
          },
          "host": {
            "filter": "Zabbix server"
          },
          "item": {
            "filter": "Number of CPUs"
          },
          "options": {
            "showDisabledItems": false,
            "skipEmptyValues": false
          },
          "proxy": {
            "filter": ""
          },
          "queryType": 0,
          "refId": "A",
          "resultFormat": "time_series",
          "table": {
            "skipEmptyValues": false
          },
          "tags": {
            "filter": ""
          },
          "trigger": {
            "filter": ""
          },
          "triggers": {
            "acknowledged": 2,
            "count": true,
            "minSeverity": 3
          }
        }
      ],
      "type": "stat"
    },
    {
      "datasource": null,
      "fieldConfig": {
        "defaults": {
          "color": {
            "mode": "thresholds"
          },
          "displayName": "Status",
          "mappings": [
            {
              "from": "",
              "id": 1,
              "text": "UP",
              "to": "",
              "type": 1,
              "value": "1"
            },
            {
              "from": "",
              "id": 2,
              "text": "Down",
              "to": "",
              "type": 1,
              "value": "0"
            }
          ],
          "thresholds": {
            "mode": "absolute",
            "steps": [
              {
                "color": "dark-green",
                "value": null
              },
              {
                "color": "rgb(255, 0, 29)",
                "value": 0
              },
              {
                "color": "dark-green",
                "value": 1
              }
            ]
          },
          "unit": "none"
        },
        "overrides": [
          {
            "matcher": {
              "id": "byName",
              "options": "Zabbix agent availability"
            },
            "properties": [
              {
                "id": "noValue",
                "value": "Down"
              }
            ]
          }
        ]
      },
      "gridPos": {
        "h": 5,
        "w": 4,
        "x": 4,
        "y": 0
      },
      "id": 4,
      "options": {
        "colorMode": "background",
        "graphMode": "none",
        "justifyMode": "center",
        "orientation": "auto",
        "reduceOptions": {
          "calcs": [
            "last"
          ],
          "fields": "",
          "values": false
        },
        "text": {},
        "textMode": "auto"
      },
      "pluginVersion": "7.5.6",
      "targets": [
        {
          "application": {
            "filter": "Status"
          },
          "functions": [],
          "group": {
            "filter": "Zabbix servers"
          },
          "host": {
            "filter": "Zabbix server"
          },
          "item": {
            "filter": "Zabbix agent availability"
          },
          "options": {
            "showDisabledItems": false,
            "skipEmptyValues": false
          },
          "proxy": {
            "filter": ""
          },
          "queryType": 0,
          "refId": "A",
          "resultFormat": "time_series",
          "table": {
            "skipEmptyValues": false
          },
          "tags": {
            "filter": ""
          },
          "trigger": {
            "filter": ""
          },
          "triggers": {
            "acknowledged": 2,
            "count": true,
            "minSeverity": 3
          }
        }
      ],
      "type": "stat"
    },
    {
      "datasource": null,
      "fieldConfig": {
        "defaults": {
          "color": {
            "mode": "thresholds"
          },
          "decimals": 0,
          "displayName": "System uptime",
          "mappings": [],
          "thresholds": {
            "mode": "absolute",
            "steps": [
              {
                "color": "dark-orange",
                "value": null
              },
              {
                "color": "dark-green",
                "value": 36000
              }
            ]
          },
          "unit": "dtdurations"
        },
        "overrides": []
      },
      "gridPos": {
        "h": 5,
        "w": 4,
        "x": 8,
        "y": 0
      },
      "id": 2,
      "options": {
        "colorMode": "background",
        "graphMode": "none",
        "justifyMode": "center",
        "orientation": "auto",
        "reduceOptions": {
          "calcs": [
            "lastNotNull"
          ],
          "fields": "",
          "values": false
        },
        "text": {},
        "textMode": "auto"
      },
      "pluginVersion": "7.5.6",
      "targets": [
        {
          "application": {
            "filter": "Status"
          },
          "functions": [],
          "group": {
            "filter": "Zabbix servers"
          },
          "host": {
            "filter": "Zabbix server"
          },
          "item": {
            "filter": "System uptime"
          },
          "options": {
            "showDisabledItems": false,
            "skipEmptyValues": false
          },
          "proxy": {
            "filter": ""
          },
          "queryType": 0,
          "refId": "A",
          "resultFormat": "time_series",
          "table": {
            "skipEmptyValues": false
          },
          "tags": {
            "filter": ""
          },
          "trigger": {
            "filter": ""
          },
          "triggers": {
            "acknowledged": 2,
            "count": true,
            "minSeverity": 3
          }
        }
      ],
      "type": "stat"
    },
    {
      "datasource": null,
      "fieldConfig": {
        "defaults": {
          "color": {
            "mode": "thresholds"
          },
          "decimals": 1,
          "displayName": "Load",
          "mappings": [],
          "thresholds": {
            "mode": "absolute",
            "steps": [
              {
                "color": "dark-orange",
                "value": null
              },
              {
                "color": "dark-red",
                "value": 3
              }
            ]
          },
          "unit": "none"
        },
        "overrides": []
      },
      "gridPos": {
        "h": 5,
        "w": 4,
        "x": 12,
        "y": 0
      },
      "id": 3,
      "options": {
        "colorMode": "background",
        "graphMode": "area",
        "justifyMode": "center",
        "orientation": "auto",
        "reduceOptions": {
          "calcs": [
            "last"
          ],
          "fields": "",
          "values": false
        },
        "text": {},
        "textMode": "auto"
      },
      "pluginVersion": "7.5.6",
      "targets": [
        {
          "application": {
            "filter": "/.*/"
          },
          "functions": [],
          "group": {
            "filter": "Zabbix servers"
          },
          "host": {
            "filter": "Zabbix server"
          },
          "item": {
            "filter": "Load average (1m avg)"
          },
          "options": {
            "showDisabledItems": false,
            "skipEmptyValues": false
          },
          "proxy": {
            "filter": ""
          },
          "queryType": 0,
          "refId": "A",
          "resultFormat": "time_series",
          "table": {
            "skipEmptyValues": false
          },
          "tags": {
            "filter": ""
          },
          "trigger": {
            "filter": ""
          },
          "triggers": {
            "acknowledged": 2,
            "count": true,
            "minSeverity": 3
          }
        }
      ],
      "type": "stat"
    },
    {
      "aliasColors": {
        "Load average (1m avg)": "dark-green",
        "Load average (5m avg)": "dark-orange",
        "Memory utilization": "rgb(77, 252, 18)",
        "proc.cpu.util(15m)": "dark-red"
      },
      "bars": false,
      "dashLength": 10,
      "dashes": false,
      "datasource": null,
      "fieldConfig": {
        "defaults": {
          "unit": "percent"
        },
        "overrides": []
      },
      "fill": 10,
      "fillGradient": 7,
      "gridPos": {
        "h": 10,
        "w": 8,
        "x": 16,
        "y": 0
      },
      "hiddenSeries": false,
      "id": 17,
      "legend": {
        "avg": false,
        "current": false,
        "max": false,
        "min": false,
        "show": true,
        "total": false,
        "values": false
      },
      "lines": true,
      "linewidth": 1,
      "nullPointMode": "null",
      "options": {
        "alertThreshold": true
      },
      "percentage": false,
      "pluginVersion": "7.5.6",
      "pointradius": 2,
      "points": false,
      "renderer": "flot",
      "seriesOverrides": [],
      "spaceLength": 10,
      "stack": false,
      "steppedLine": false,
      "targets": [
        {
          "application": {
            "filter": "Memory"
          },
          "functions": [],
          "group": {
            "filter": "Zabbix servers"
          },
          "host": {
            "filter": "Zabbix server"
          },
          "item": {
            "filter": "Memory utilization"
          },
          "options": {
            "showDisabledItems": false,
            "skipEmptyValues": false
          },
          "proxy": {
            "filter": ""
          },
          "queryType": 0,
          "refId": "A",
          "resultFormat": "time_series",
          "table": {
            "skipEmptyValues": false
          },
          "tags": {
            "filter": ""
          },
          "trigger": {
            "filter": ""
          },
          "triggers": {
            "acknowledged": 2,
            "count": true,
            "minSeverity": 3
          }
        }
      ],
      "thresholds": [],
      "timeFrom": null,
      "timeRegions": [],
      "timeShift": null,
      "title": "Memory utilization",
      "tooltip": {
        "shared": true,
        "sort": 0,
        "value_type": "individual"
      },
      "type": "graph",
      "xaxis": {
        "buckets": null,
        "mode": "time",
        "name": null,
        "show": true,
        "values": []
      },
      "yaxes": [
        {
          "$$hashKey": "object:2172",
          "format": "percent",
          "label": null,
          "logBase": 1,
          "max": null,
          "min": null,
          "show": true
        },
        {
          "$$hashKey": "object:2173",
          "format": "short",
          "label": null,
          "logBase": 1,
          "max": null,
          "min": null,
          "show": true
        }
      ],
      "yaxis": {
        "align": false,
        "alignLevel": null
      }
    },
    {
      "datasource": null,
      "fieldConfig": {
        "defaults": {
          "color": {
            "mode": "thresholds"
          },
          "mappings": [],
          "thresholds": {
            "mode": "absolute",
            "steps": [
              {
                "color": "dark-green",
                "value": null
              }
            ]
          },
          "unit": "decbytes"
        },
        "overrides": []
      },
      "gridPos": {
        "h": 2,
        "w": 2,
        "x": 0,
        "y": 3
      },
      "id": 11,
      "options": {
        "colorMode": "value",
        "graphMode": "none",
        "justifyMode": "center",
        "orientation": "auto",
        "reduceOptions": {
          "calcs": [
            "lastNotNull"
          ],
          "fields": "",
          "values": false
        },
        "text": {},
        "textMode": "auto"
      },
      "pluginVersion": "7.5.6",
      "targets": [
        {
          "application": {
            "filter": "/.*/"
          },
          "functions": [],
          "group": {
            "filter": "Zabbix servers"
          },
          "host": {
            "filter": "Zabbix server"
          },
          "item": {
            "filter": "/: Total space"
          },
          "options": {
            "showDisabledItems": false,
            "skipEmptyValues": false
          },
          "proxy": {
            "filter": ""
          },
          "queryType": 0,
          "refId": "A",
          "resultFormat": "time_series",
          "table": {
            "skipEmptyValues": false
          },
          "tags": {
            "filter": ""
          },
          "trigger": {
            "filter": ""
          },
          "triggers": {
            "acknowledged": 2,
            "count": true,
            "minSeverity": 3
          }
        }
      ],
      "type": "stat"
    },
    {
      "datasource": null,
      "fieldConfig": {
        "defaults": {
          "color": {
            "mode": "thresholds"
          },
          "mappings": [],
          "thresholds": {
            "mode": "absolute",
            "steps": [
              {
                "color": "dark-green",
                "value": null
              }
            ]
          },
          "unit": "decbytes"
        },
        "overrides": []
      },
      "gridPos": {
        "h": 2,
        "w": 2,
        "x": 2,
        "y": 3
      },
      "id": 12,
      "options": {
        "colorMode": "value",
        "graphMode": "none",
        "justifyMode": "center",
        "orientation": "auto",
        "reduceOptions": {
          "calcs": [
            "lastNotNull"
          ],
          "fields": "",
          "values": false
        },
        "text": {},
        "textMode": "auto"
      },
      "pluginVersion": "7.5.6",
      "targets": [
        {
          "application": {
            "filter": "/.*/"
          },
          "functions": [],
          "group": {
            "filter": "Zabbix servers"
          },
          "host": {
            "filter": "Zabbix server"
          },
          "item": {
            "filter": "/: Used space"
          },
          "options": {
            "showDisabledItems": false,
            "skipEmptyValues": false
          },
          "proxy": {
            "filter": ""
          },
          "queryType": 0,
          "refId": "A",
          "resultFormat": "time_series",
          "table": {
            "skipEmptyValues": false
          },
          "tags": {
            "filter": ""
          },
          "trigger": {
            "filter": ""
          },
          "triggers": {
            "acknowledged": 2,
            "count": true,
            "minSeverity": 3
          }
        }
      ],
      "type": "stat"
    },
    {
      "datasource": null,
      "fieldConfig": {
        "defaults": {
          "color": {
            "mode": "thresholds"
          },
          "decimals": 1,
          "mappings": [],
          "thresholds": {
            "mode": "absolute",
            "steps": [
              {
                "color": "rgb(31, 255, 0)",
                "value": null
              },
              {
                "color": "rgb(255, 0, 29)",
                "value": 90
              }
            ]
          },
          "unit": "percent"
        },
        "overrides": []
      },
      "gridPos": {
        "h": 5,
        "w": 6,
        "x": 0,
        "y": 5
      },
      "id": 14,
      "options": {
        "reduceOptions": {
          "calcs": [
            "last"
          ],
          "fields": "",
          "values": false
        },
        "showThresholdLabels": false,
        "showThresholdMarkers": true,
        "text": {}
      },
      "pluginVersion": "7.5.6",
      "targets": [
        {
          "application": {
            "filter": "CPU"
          },
          "functions": [],
          "group": {
            "filter": "Zabbix servers"
          },
          "host": {
            "filter": "Zabbix server"
          },
          "item": {
            "filter": "proc.cpu.util (1m)"
          },
          "options": {
            "showDisabledItems": false,
            "skipEmptyValues": false
          },
          "proxy": {
            "filter": ""
          },
          "queryType": 0,
          "refId": "A",
          "resultFormat": "time_series",
          "table": {
            "skipEmptyValues": false
          },
          "tags": {
            "filter": ""
          },
          "trigger": {
            "filter": ""
          },
          "triggers": {
            "acknowledged": 2,
            "count": true,
            "minSeverity": 3
          }
        }
      ],
      "title": "CPU utlization",
      "type": "gauge"
    },
    {
      "datasource": null,
      "fieldConfig": {
        "defaults": {
          "color": {
            "mode": "thresholds"
          },
          "decimals": 1,
          "mappings": [],
          "thresholds": {
            "mode": "absolute",
            "steps": [
              {
                "color": "rgb(31, 255, 0)",
                "value": null
              },
              {
                "color": "rgb(255, 0, 29)",
                "value": 90
              }
            ]
          },
          "unit": "percent"
        },
        "overrides": []
      },
      "gridPos": {
        "h": 5,
        "w": 5,
        "x": 6,
        "y": 5
      },
      "id": 15,
      "options": {
        "reduceOptions": {
          "calcs": [
            "last"
          ],
          "fields": "",
          "values": false
        },
        "showThresholdLabels": false,
        "showThresholdMarkers": true,
        "text": {}
      },
      "pluginVersion": "7.5.6",
      "targets": [
        {
          "application": {
            "filter": "Memory"
          },
          "functions": [],
          "group": {
            "filter": "Zabbix servers"
          },
          "host": {
            "filter": "Zabbix server"
          },
          "item": {
            "filter": "Memory utilization"
          },
          "options": {
            "showDisabledItems": false,
            "skipEmptyValues": false
          },
          "proxy": {
            "filter": ""
          },
          "queryType": 0,
          "refId": "A",
          "resultFormat": "time_series",
          "table": {
            "skipEmptyValues": false
          },
          "tags": {
            "filter": ""
          },
          "trigger": {
            "filter": ""
          },
          "triggers": {
            "acknowledged": 2,
            "count": true,
            "minSeverity": 3
          }
        }
      ],
      "title": "Memory utlization",
      "type": "gauge"
    },
    {
      "datasource": null,
      "fieldConfig": {
        "defaults": {
          "color": {
            "mode": "thresholds"
          },
          "decimals": 1,
          "mappings": [],
          "thresholds": {
            "mode": "absolute",
            "steps": [
              {
                "color": "rgb(31, 255, 0)",
                "value": null
              },
              {
                "color": "rgb(255, 0, 29)",
                "value": 90
              }
            ]
          },
          "unit": "percent"
        },
        "overrides": []
      },
      "gridPos": {
        "h": 5,
        "w": 5,
        "x": 11,
        "y": 5
      },
      "id": 16,
      "options": {
        "reduceOptions": {
          "calcs": [
            "last"
          ],
          "fields": "",
          "values": false
        },
        "showThresholdLabels": false,
        "showThresholdMarkers": true,
        "text": {}
      },
      "pluginVersion": "7.5.6",
      "targets": [
        {
          "application": {
            "filter": "Filesystem /"
          },
          "functions": [],
          "group": {
            "filter": "Zabbix servers"
          },
          "host": {
            "filter": "Zabbix server"
          },
          "item": {
            "filter": "/: Space utilization"
          },
          "options": {
            "showDisabledItems": false,
            "skipEmptyValues": false
          },
          "proxy": {
            "filter": ""
          },
          "queryType": 0,
          "refId": "A",
          "resultFormat": "time_series",
          "table": {
            "skipEmptyValues": false
          },
          "tags": {
            "filter": ""
          },
          "trigger": {
            "filter": ""
          },
          "triggers": {
            "acknowledged": 2,
            "count": true,
            "minSeverity": 3
          }
        }
      ],
      "title": "Space utlization",
      "type": "gauge"
    },
    {
      "aliasColors": {
        "Load average (1m avg)": "dark-green",
        "Load average (5m avg)": "dark-orange",
        "proc.cpu.util (15m)": "dark-red",
        "proc.cpu.util (1m)": "dark-green",
        "proc.cpu.util (5m)": "dark-orange",
        "proc.cpu.util(15m)": "dark-red"
      },
      "bars": false,
      "dashLength": 10,
      "dashes": false,
      "datasource": null,
      "fieldConfig": {
        "defaults": {},
        "overrides": []
      },
      "fill": 1,
      "fillGradient": 9,
      "gridPos": {
        "h": 9,
        "w": 12,
        "x": 0,
        "y": 10
      },
      "hiddenSeries": false,
      "id": 6,
      "legend": {
        "avg": false,
        "current": false,
        "max": false,
        "min": false,
        "show": true,
        "total": false,
        "values": false
      },
      "lines": true,
      "linewidth": 1,
      "nullPointMode": "null",
      "options": {
        "alertThreshold": true
      },
      "percentage": false,
      "pluginVersion": "7.5.6",
      "pointradius": 2,
      "points": false,
      "renderer": "flot",
      "seriesOverrides": [],
      "spaceLength": 10,
      "stack": false,
      "steppedLine": false,
      "targets": [
        {
          "application": {
            "filter": "CPU"
          },
          "functions": [],
          "group": {
            "filter": "Zabbix servers"
          },
          "host": {
            "filter": "Zabbix server"
          },
          "item": {
            "filter": "proc.cpu.util (15m)"
          },
          "options": {
            "showDisabledItems": false,
            "skipEmptyValues": false
          },
          "proxy": {
            "filter": ""
          },
          "queryType": 0,
          "refId": "A",
          "resultFormat": "time_series",
          "table": {
            "skipEmptyValues": false
          },
          "tags": {
            "filter": ""
          },
          "trigger": {
            "filter": ""
          },
          "triggers": {
            "acknowledged": 2,
            "count": true,
            "minSeverity": 3
          }
        },
        {
          "application": {
            "filter": "CPU"
          },
          "functions": [],
          "group": {
            "filter": "Zabbix servers"
          },
          "hide": false,
          "host": {
            "filter": "Zabbix server"
          },
          "item": {
            "filter": "proc.cpu.util (5m)"
          },
          "options": {
            "showDisabledItems": false,
            "skipEmptyValues": false
          },
          "proxy": {
            "filter": ""
          },
          "queryType": 0,
          "refId": "B",
          "resultFormat": "time_series",
          "table": {
            "skipEmptyValues": false
          },
          "tags": {
            "filter": ""
          },
          "trigger": {
            "filter": ""
          },
          "triggers": {
            "acknowledged": 2,
            "count": true,
            "minSeverity": 3
          }
        },
        {
          "application": {
            "filter": "CPU"
          },
          "functions": [],
          "group": {
            "filter": "Zabbix servers"
          },
          "hide": false,
          "host": {
            "filter": "Zabbix server"
          },
          "item": {
            "filter": "proc.cpu.util (1m)"
          },
          "options": {
            "showDisabledItems": false,
            "skipEmptyValues": false
          },
          "proxy": {
            "filter": ""
          },
          "queryType": 0,
          "refId": "C",
          "resultFormat": "time_series",
          "table": {
            "skipEmptyValues": false
          },
          "tags": {
            "filter": ""
          },
          "trigger": {
            "filter": ""
          },
          "triggers": {
            "acknowledged": 2,
            "count": true,
            "minSeverity": 3
          }
        }
      ],
      "thresholds": [],
      "timeFrom": null,
      "timeRegions": [],
      "timeShift": null,
      "title": "CPU utilization over time",
      "tooltip": {
        "shared": true,
        "sort": 0,
        "value_type": "individual"
      },
      "type": "graph",
      "xaxis": {
        "buckets": null,
        "mode": "time",
        "name": null,
        "show": true,
        "values": []
      },
      "yaxes": [
        {
          "$$hashKey": "object:2172",
          "format": "short",
          "label": null,
          "logBase": 1,
          "max": null,
          "min": null,
          "show": true
        },
        {
          "$$hashKey": "object:2173",
          "format": "short",
          "label": null,
          "logBase": 1,
          "max": null,
          "min": null,
          "show": true
        }
      ],
      "yaxis": {
        "align": false,
        "alignLevel": null
      }
    },
    {
      "aliasColors": {
        "Load average (15m avg)": "rgb(247, 3, 31)",
        "Load average (1m avg)": "dark-green",
        "Load average (5m avg)": "dark-orange",
        "proc.cpu.util(15m)": "dark-red"
      },
      "bars": false,
      "dashLength": 10,
      "dashes": false,
      "datasource": null,
      "fieldConfig": {
        "defaults": {},
        "overrides": []
      },
      "fill": 1,
      "fillGradient": 2,
      "gridPos": {
        "h": 9,
        "w": 12,
        "x": 12,
        "y": 10
      },
      "hiddenSeries": false,
      "id": 7,
      "legend": {
        "avg": false,
        "current": false,
        "max": false,
        "min": false,
        "show": true,
        "total": false,
        "values": false
      },
      "lines": true,
      "linewidth": 1,
      "nullPointMode": "null",
      "options": {
        "alertThreshold": true
      },
      "percentage": false,
      "pluginVersion": "7.5.6",
      "pointradius": 2,
      "points": false,
      "renderer": "flot",
      "seriesOverrides": [],
      "spaceLength": 10,
      "stack": false,
      "steppedLine": false,
      "targets": [
        {
          "application": {
            "filter": "CPU"
          },
          "functions": [],
          "group": {
            "filter": "Zabbix servers"
          },
          "host": {
            "filter": "Zabbix server"
          },
          "item": {
            "filter": "Load average (15m avg)"
          },
          "options": {
            "showDisabledItems": false,
            "skipEmptyValues": false
          },
          "proxy": {
            "filter": ""
          },
          "queryType": 0,
          "refId": "A",
          "resultFormat": "time_series",
          "table": {
            "skipEmptyValues": false
          },
          "tags": {
            "filter": ""
          },
          "trigger": {
            "filter": ""
          },
          "triggers": {
            "acknowledged": 2,
            "count": true,
            "minSeverity": 3
          }
        },
        {
          "application": {
            "filter": "CPU"
          },
          "functions": [],
          "group": {
            "filter": "Zabbix servers"
          },
          "hide": false,
          "host": {
            "filter": "Zabbix server"
          },
          "item": {
            "filter": "Load average (5m avg)"
          },
          "options": {
            "showDisabledItems": false,
            "skipEmptyValues": false
          },
          "proxy": {
            "filter": ""
          },
          "queryType": 0,
          "refId": "B",
          "resultFormat": "time_series",
          "table": {
            "skipEmptyValues": false
          },
          "tags": {
            "filter": ""
          },
          "trigger": {
            "filter": ""
          },
          "triggers": {
            "acknowledged": 2,
            "count": true,
            "minSeverity": 3
          }
        },
        {
          "application": {
            "filter": "CPU"
          },
          "functions": [],
          "group": {
            "filter": "Zabbix servers"
          },
          "hide": false,
          "host": {
            "filter": "Zabbix server"
          },
          "item": {
            "filter": "Load average (1m avg)"
          },
          "options": {
            "showDisabledItems": false,
            "skipEmptyValues": false
          },
          "proxy": {
            "filter": ""
          },
          "queryType": 0,
          "refId": "C",
          "resultFormat": "time_series",
          "table": {
            "skipEmptyValues": false
          },
          "tags": {
            "filter": ""
          },
          "trigger": {
            "filter": ""
          },
          "triggers": {
            "acknowledged": 2,
            "count": true,
            "minSeverity": 3
          }
        }
      ],
      "thresholds": [],
      "timeFrom": null,
      "timeRegions": [],
      "timeShift": null,
      "title": "Load Average over time",
      "tooltip": {
        "shared": true,
        "sort": 0,
        "value_type": "individual"
      },
      "type": "graph",
      "xaxis": {
        "buckets": null,
        "mode": "time",
        "name": null,
        "show": true,
        "values": []
      },
      "yaxes": [
        {
          "$$hashKey": "object:2172",
          "format": "short",
          "label": null,
          "logBase": 1,
          "max": null,
          "min": null,
          "show": true
        },
        {
          "$$hashKey": "object:2173",
          "format": "short",
          "label": null,
          "logBase": 1,
          "max": null,
          "min": null,
          "show": true
        }
      ],
      "yaxis": {
        "align": false,
        "alignLevel": null
      }
    },
    {
      "activeThemeId": 1,
      "datasource": null,
      "disableThemePicker": true,
      "fieldConfig": {
        "defaults": {},
        "overrides": []
      },
      "gridPos": {
        "h": 1,
        "w": 24,
        "x": 0,
        "y": 19
      },
      "id": 19,
      "pluginVersion": "7.5.6",
      "targets": [
        {
          "application": {
            "filter": ""
          },
          "functions": [],
          "group": {
            "filter": ""
          },
          "host": {
            "filter": ""
          },
          "item": {
            "filter": ""
          },
          "options": {
            "showDisabledItems": false,
            "skipEmptyValues": false
          },
          "proxy": {
            "filter": ""
          },
          "queryType": 0,
          "refId": "A",
          "resultFormat": "time_series",
          "table": {
            "skipEmptyValues": false
          },
          "tags": {
            "filter": ""
          },
          "trigger": {
            "filter": ""
          },
          "triggers": {
            "acknowledged": 2,
            "count": true,
            "minSeverity": 3
          }
        }
      ],
      "themes": [
        {
          "name": "Night Theme",
          "styles": [
            {
              "props": {
                "theme": "default"
              },
              "type": "basetheme"
            },
            {
              "props": {
                "url": "https://images.unsplash.com/photo-1524334228333-0f6db392f8a1"
              },
              "type": "bgimage"
            },
            {
              "props": {
                "text": ".panel-container {\n    background-color: rgba(0,0,0,0.3);\n}"
              },
              "type": "style"
            }
          ]
        },
        {
          "name": "Theme 2",
          "styles": [
            {
              "props": {
                "theme": "default"
              },
              "type": "basetheme"
            },
            {
              "props": {
                "url": "https://i.imgur.com/dvTftFe.jpg"
              },
              "type": "bgimage"
            },
            {
              "props": {
                "url": ""
              },
              "type": "url"
            },
            {
              "props": {
                "text": ".panel-container {\n    background-color: rgba(0,0,0,0.3);\n}"
              },
              "type": "style"
            }
          ]
        }
      ],
      "timeFrom": null,
      "timeShift": null,
      "transparent": true,
      "type": "yesoreyeram-boomtheme-panel"
    }
  ],
  "refresh": "5s",
  "schemaVersion": 27,
  "style": "dark",
  "tags": [],
  "templating": {
    "list": []
  },
  "time": {
    "from": "now-6h",
    "to": "now"
  },
  "timepicker": {
    "hidden": false
  },
  "timezone": "",
  "title": "Zabbix Teste 21 05 2021 Playlist 02",
  "uid": "LNl7uCCGz",
  "version": 28
}